{
  "indexTitle": "Core packages & features",
  "sidebar": [
    {
      "text": "Find and replace",
      "link": "/core-packages-and-features/find-and-replace",
      "summary": "Find and replace within buffers and across the project."
    },
    {
      "text": "Snippets",
      "link": "/core-packages-and-features/snippets",
      "summary": "Expand text via special prefixes or via the autocomplete menu."
    },
    {
      "text": "Autocomplete",
      "link": "/core-packages-and-features/autocomplete",
      "summary": "Work with suggested autocompletions as you type."
    },
    {
      "text": "Version control",
      "link": "/core-packages-and-features/version-control",
      "summary": "Keep a history of your files’ changes."
    },
    {
      "text": "GitHub package",
      "link": "/core-packages-and-features/github-package",
      "summary": "Integrate with GitHub from within Pulsar."
    },
    {
      "text": "Spell check",
      "link": "/core-packages-and-features/spell-check",
      "summary": "Fix misspellings in your text."
    },
    {
      "text": "Previews",
      "link": "/core-packages-and-features/previews",
      "summary": "See what your prose files look like rendered."
    },
    {
      "text": "Folding",
      "link": "/core-packages-and-features/folding",
      "summary": "Collapse text in a file."
    },
    {
      "text": "Panes",
      "link": "/core-packages-and-features/panes",
      "summary": "Understand how items are arranged in the Pulsar workspace."
    },
    {
      "text": "Choosing a grammar",
      "link": "/core-packages-and-features/choosing-a-grammar",
      "summary": "Learn how Pulsar decides how to syntax-highlight a file."
    }
  ]
}
